{
  "project_info": {
    "project_number": "1068162247377",
    "project_id": "flutter-shop-mds",
    "storage_bucket": "flutter-shop-mds.firebasestorage.app"
  },
  "client": [
    {
      "client_info": {
        "mobilesdk_app_id": "1:1068162247377:android:ed95f84ba277e26412f3f0",
        "android_client_info": {
          "package_name": "com.example.flutter_shop"
        }
      },
      "oauth_client": [
        {
          "client_id": "1068162247377-tvarsnmeimvta9uo8egmpilk98qpinfg.apps.googleusercontent.com",
          "client_type": 3
        }
      ],
      "api_key": [
        {
          "current_key": "AIzaSyCs1NOgf6IuG4q6_5BO84atdB3xy4oW4OM"
        }
      ],
      "services": {
        "appinvite_service": {
          "other_platform_oauth_client": [
            {
              "client_id": "1068162247377-tvarsnmeimvta9uo8egmpilk98qpinfg.apps.googleusercontent.com",
              "client_type": 3
            },
            {
              "client_id": "1068162247377-pgf2ua7ghoiarpvdcc06768afbf3rsi9.apps.googleusercontent.com",
              "client_type": 2,
              "ios_info": {
                "bundle_id": "com.example.flutterShop"
              }
            }
          ]
        }
      }
    }
  ],
  "configuration_version": "1"
}